matchernet/__init__.py
matchernet/ekf.py
matchernet/fn.py
matchernet/matchernet.py
matchernet/matchernet_null.py
matchernet/observer.py
matchernet/state.py
matchernet/state_space_model_2d.py
matchernet/utils.py
matchernet/control/__init__.py
matchernet/control/control.py
matchernet/control/ilqg.py
matchernet/control/mpc.py
matchernet/control/mpcenv.py
matchernet/control/multi.py
matchernet/log/__init__.py
matchernet/log/logging.json
matchernet/log/logging_conf.py
matchernet/misc/__init__.py
matchernet/misc/recording.py
matchernet-0.1.0.dist-info/LICENSE
matchernet-0.1.0.dist-info/METADATA
matchernet-0.1.0.dist-info/WHEEL
matchernet-0.1.0.dist-info/top_level.txt
matchernet-0.1.0.dist-info/RECORD
