Metadata-Version: 2.1
Name: matchernet
Version: 0.1.0
Summary: UNKNOWN
Home-page: https://github.com/shigeyukioba/matchernet
Author: Shigeyuki Oba
Author-email: oba@i.kyoto-u.ac.jp
License: Apache License 2.0
Keywords: kalman filter,neural net
Platform: UNKNOWN
Classifier: Programming Language :: Python
Classifier: Programming Language :: Python :: 3
Classifier: Programming Language :: Python :: 3.7
Classifier: Topic :: Software Development :: Libraries :: Python Modules
Requires-Dist: autograd (==1.3)
Requires-Dist: matplotlib (==3.1.1)
Requires-Dist: numpy (==1.17.3)
Requires-Dist: BriCA2 (==0.5.0)
Requires-Dist: opencv-python (==4.0.0.21)
Requires-Dist: pygame (==1.9.6)
Requires-Dist: pyglet (==1.3.2)
Requires-Dist: sympy (==1.3)
Requires-Dist: cloudpickle (==1.2.2)
